Pylol/functions.py
Pylol/osfuncs.py
Pylol/randfuncs.py
Pylol/timefuncs.py
pylol-1.0.12.dist-info/LICENSE
pylol-1.0.12.dist-info/METADATA
pylol-1.0.12.dist-info/WHEEL
pylol-1.0.12.dist-info/top_level.txt
pylol-1.0.12.dist-info/RECORD
