Metadata-Version: 2.1
Name: pylol
Version: 1.0.12
Summary: A Module to get basic modules like the Time Module and Math Modules and combine them into one so you don't need to import so many modules!
Home-page: https://gist.github.com/BXRSRUDIOS
Author: BXRCODES
Author-email: 19braja@rgshw.com
License: MIT
Keywords: core package
Platform: UNKNOWN
Classifier: License :: OSI Approved :: MIT License
Classifier: Programming Language :: Python :: 3
Classifier: Operating System :: OS Independent
